examples/physeng/ex_geometry.py
examples/physeng/ex_humidity.py
examples/physeng/ex_iso2768.py
examples/physeng/ex_iso286.py
examples/physeng/ex_layup.py
examples/physeng/ex_ply.py
physeng/__init__.py
physeng/humidity.py
physeng/iso2768.py
physeng/iso286.py
physeng/matplotlib.py
physeng/singleton.py
physeng/units.py
physeng/utilities.py
physeng/data/ISO2768Length.csv
physeng/data/ISO286Hole.csv
physeng/data/ISO286Shaft.csv
physeng/data/MaterialDB_alloys.xml
physeng/data/MaterialDB_ceramics.xml
physeng/data/MaterialDB_composites.xml
physeng/data/MaterialDB_compounds.xml
physeng/data/MaterialDB_elements.xml
physeng/data/MaterialDB_fluids.xml
physeng/data/MaterialDB_polymers.xml
physeng/data/__init__.py
physeng/geometry/__init__.py
physeng/geometry/geometry.py
physeng/geometry/line2D.py
physeng/geometry/line3D.py
physeng/geometry/plane3D.py
physeng/geometry/point2D.py
physeng/geometry/point3D.py
physeng/geometry/vector2D.py
physeng/geometry/vector3D.py
physeng/materials/__init__.py
physeng/materials/isotropicmaterial.py
physeng/materials/layup.py
physeng/materials/material.py
physeng/materials/materialdb.py
physeng/materials/materialproperty.py
physeng/materials/orthotropicmaterial.py
physeng/materials/ply.py
physeng/materials/utilities.py
physeng-0.9.0.dist-info/METADATA
physeng-0.9.0.dist-info/WHEEL
physeng-0.9.0.dist-info/top_level.txt
physeng-0.9.0.dist-info/RECORD
